Processor_MIPS32-main/processor_pipeline/processor_pipeline.srcs/sources_1/new/pipeline.v
`timescale 1ns / 1ps
//////////////////////////////////////////////////////////////////////////////////
// Company: 
// Engineer: 
// 
// Design Name: 
// Module Name: pipeline
// Project Name: 
// Target Devices: 
// Tool Versions: 
// Description: 
// 
// Dependencies: 
// 
// Revision:
// Revision 0.01 - File Created
// Additional Comments:
// 
//////////////////////////////////////////////////////////////////////////////////


//===========================================================
// 5-Stage Pipelined Processor in Verilog
// Stages: IF, ID, EX, MEM, WB
//===========================================================

module pipeline(clk1, clk2);
    input clk1, clk2;

    // ---------------- Pipeline Registers ----------------
    reg [31:0] PC, IF_ID_IR, IF_ID_NPC;
    reg [31:0] ID_EX_IR, ID_EX_NPC, ID_EX_A, ID_EX_B, ID_EX_Imm;
    reg [31:0] EX_MEM_IR, EX_MEM_ALUOut, EX_MEM_B;
    reg [31:0] MEM_WB_IR, MEM_WB_ALUOut, MEM_WB_LMD;

    // ---------------- Supporting Registers ----------------
    reg [31:0] Reg [0:31];   // Register File
    reg [31:0] Mem [0:1023]; // Memory
    reg [2:0]  ID_EX_type, EX_MEM_type, MEM_WB_type;

    reg HALTED, TAKEN_BRANCH;

    // ---------------- Instruction Opcodes ----------------
    parameter ADD   = 6'b000000, SUB   = 6'b000001, AND  = 6'b000010,
              OR    = 6'b000011, SLT   = 6'b000100, MUL  = 6'b000101,
              ADDI  = 6'b000110, SUBI  = 6'b000111, SLTI = 6'b001000,
              LW    = 6'b001001, SW    = 6'b001010,
              BNEQZ = 6'b001011, BEQZ = 6'b001100,
              HLT   = 6'b111111;

    // ---------------- Instruction Types ----------------
    parameter RR_ALU = 3'b000, RM_ALU = 3'b001, LOAD = 3'b010,
              STORE  = 3'b011, BRANCH = 3'b100, HALT = 3'b101;

    //===========================================================
    // IF Stage
    //===========================================================
    always @(posedge clk1)
        if (HALTED == 0) begin
            if ((EX_MEM_type == BRANCH) && (TAKEN_BRANCH == 1)) begin
                IF_ID_IR  <= #2 Mem[EX_MEM_ALUOut]; 
                IF_ID_NPC <= #2 EX_MEM_ALUOut + 1;
                PC        <= #2 EX_MEM_ALUOut + 1;
                TAKEN_BRANCH <= 0;
            end
            else begin
                IF_ID_IR  <= #2 Mem[PC];
                IF_ID_NPC <= #2 PC + 1;
                PC        <= #2 PC + 1;
            end
        end

    //===========================================================
    // ID Stage
    //===========================================================
    always @(posedge clk2)
        if (HALTED == 0) begin
            // Read "rs"
            if (IF_ID_IR[25:21] == 5'b00000) 
                ID_EX_A <= 0;
            else 
                ID_EX_A <= #2 Reg[IF_ID_IR[25:21]];   // rs

            // Read "rt"
            if (IF_ID_IR[20:16] == 5'b00000) 
                ID_EX_B <= 0;
            else 
                ID_EX_B <= #2 Reg[IF_ID_IR[20:16]];   // rt

            ID_EX_NPC  <= #2 IF_ID_NPC;
            ID_EX_IR   <= #2 IF_ID_IR;
            ID_EX_Imm  <= #2 {{16{IF_ID_IR[15]}}, IF_ID_IR[15:0]}; // sign-extension

            // Decode instruction type
            case (IF_ID_IR[31:26])
                ADD, SUB, AND, OR, SLT, MUL:  ID_EX_type <= #2 RR_ALU;
                ADDI, SUBI, SLTI:             ID_EX_type <= #2 RM_ALU;
                LW:                            ID_EX_type <= #2 LOAD;
                SW:                            ID_EX_type <= #2 STORE;
                BNEQZ, BEQZ:                   ID_EX_type <= #2 BRANCH;
                HLT:                           ID_EX_type <= #2 HALT;
                default:                       ID_EX_type <= #2 HALT; // invalid
            endcase
        end

    //===========================================================
    // EX Stage
    //===========================================================
    always @(posedge clk1)
        if (HALTED == 0) begin
            EX_MEM_type <= ID_EX_type;
            EX_MEM_IR   <= ID_EX_IR;

            case (ID_EX_type)
                RR_ALU: begin
                    case (ID_EX_IR[31:26])
                        ADD:  EX_MEM_ALUOut <= #2 ID_EX_A + ID_EX_B;
                        SUB:  EX_MEM_ALUOut <= #2 ID_EX_A - ID_EX_B;
                        AND:  EX_MEM_ALUOut <= #2 ID_EX_A & ID_EX_B;
                        OR:   EX_MEM_ALUOut <= #2 ID_EX_A | ID_EX_B;
                        SLT:  EX_MEM_ALUOut <= #2 (ID_EX_A < ID_EX_B);
                        MUL:  EX_MEM_ALUOut <= #2 ID_EX_A * ID_EX_B;
                        default: EX_MEM_ALUOut <= 0;
                    endcase
                end

                RM_ALU: begin
                    case (ID_EX_IR[31:26])
                        ADDI: EX_MEM_ALUOut <= #2 ID_EX_A + ID_EX_Imm;
                        SUBI: EX_MEM_ALUOut <= #2 ID_EX_A - ID_EX_Imm;
                        SLTI: EX_MEM_ALUOut <= #2 (ID_EX_A < ID_EX_Imm);
                        default: EX_MEM_ALUOut <= 0;
                    endcase
                end

                LOAD, STORE: begin
                    EX_MEM_ALUOut <= #2 ID_EX_A + ID_EX_Imm;
                    EX_MEM_B      <= #2 ID_EX_B;
                end

                BRANCH: begin
                    if ((ID_EX_IR[31:26] == BEQZ) && (ID_EX_A == 0))
                        TAKEN_BRANCH <= 1;
                    else if ((ID_EX_IR[31:26] == BNEQZ) && (ID_EX_A != 0))
                        TAKEN_BRANCH <= 1;
                    else
                        TAKEN_BRANCH <= 0;

                    if (TAKEN_BRANCH)
                        EX_MEM_ALUOut <= #2 ID_EX_NPC + ID_EX_Imm;
                end
            endcase
        end

    //===========================================================
    // MEM Stage
    //===========================================================
   
// Initialization at start (processor module ke andar)
initial begin
    MEM_WB_LMD = 32'b0;
    MEM_WB_ALUOut = 32'b0;
    MEM_WB_IR = 32'b0;
end

// MEM stage
always @(posedge clk2)
    if (HALTED == 0) begin
        MEM_WB_type <= EX_MEM_type;
        MEM_WB_IR   <= #2 EX_MEM_IR;

        case (EX_MEM_type)
            RR_ALU, RM_ALU:
                MEM_WB_ALUOut <= #2 EX_MEM_ALUOut;

            LOAD:
                MEM_WB_LMD <= #2 Mem[EX_MEM_ALUOut];

            STORE:
                if (TAKEN_BRANCH == 0)
                    Mem[EX_MEM_ALUOut] <= #2 EX_MEM_B;

            default: begin
                MEM_WB_LMD    <= MEM_WB_LMD;     // hold previous value
                MEM_WB_ALUOut <= MEM_WB_ALUOut; // hold previous value
            end
        endcase
    end

    //===========================================================
    // WB Stage
    //===========================================================
    always @(posedge clk1) begin
        if (TAKEN_BRANCH == 0) begin // disable write if branch taken
            case (MEM_WB_type)
                RR_ALU:
                    Reg[MEM_WB_IR[15:11]] <= #2 MEM_WB_ALUOut; // "rd"

                RM_ALU:
                    Reg[MEM_WB_IR[20:16]] <= #2 MEM_WB_ALUOut; // "rt"

                LOAD:
                    Reg[MEM_WB_IR[20:16]] <= #2 MEM_WB_LMD;    // "rt"

                HALT:
                    HALTED <= #2 1'b1;
            endcase
        end
    end
endmodule

Processor_MIPS32-main/processor_pipeline/processor_pipeline.srcs/sim_1/new/test_processor.v
`timescale 1ns / 1ps
//////////////////////////////////////////////////////////////////////////////////
// Company: 
// Engineer: 
// 
// Design Name: 
// Module Name: test_processor
// Project Name: 
// Target Devices: 
// Tool Versions: 
// Description: 
// 
// Dependencies: 
// 
// Revision:
// Revision 0.01 - File Created
// Additional Comments:
// 
//////////////////////////////////////////////////////////////////////////////////


//===========================================================
// Testbench for Pipelined Processor
//===========================================================

module test_processor;
    reg clk1, clk2;
    integer k;

    // DUT (Device Under Test)
    pipeline mips (clk1, clk2);

    // ---------------- CLOCK GENERATION ----------------
    initial begin
        clk1 = 0; clk2 = 0;                 // two-phase clock
        repeat (50) begin
            #5 clk1 = 1; #5 clk1 = 0;
            #5 clk2 = 1; #5 clk2 = 0;
        end
    end

    // ---------------- PROGRAM & INITIALIZATION ----------------
    initial begin
    for (k = 0; k < 1024; k = k + 1)
        mips.Mem[k] = 32'b0;
    for (k = 0; k < 32; k = k + 1)
        mips.Reg[k] = 32'b0;
end

    initial begin
        // initialize registers
        for (k = 0; k < 31; k = k + 1) begin
            mips.Reg[k] = k;
        end

        // load program in memory
        mips.Mem[0]  = 32'h280a00c8;  // ADDI R10,R0,200
        mips.Mem[1]  = 32'h28020001;  // ADDI R2,R0,1
        mips.Mem[2]  = 32'h0e94a000;  // OR R20,R20,R20 -- dummy
        mips.Mem[3]  = 32'h21430000;  // LW R3,0(R10)
        mips.Mem[4]  = 32'h0e94a000;  // OR R20,R20,R20 -- dummy
        mips.Mem[5]  = 32'h14431000;  // Loop: MUL R2,R2,R3
        mips.Mem[6]  = 32'h2c630001;  // SUBI R3,R3,1
        mips.Mem[7]  = 32'h0e94a000;  // OR R20,R20,R20 -- dummy
        mips.Mem[8]  = 32'h3460fffc;  // BNEQZ R3,Loop (offset -4)
        mips.Mem[9]  = 32'h2542fffe;  // SW R2,-2(R10)
        mips.Mem[10] = 32'hfc000000;  // HLT

        // data memory initialization
        mips.Mem[200] = 7;            // factorial of 7

        // init control signals
        mips.PC = 0;
        mips.HALTED = 0;
        mips.TAKEN_BRANCH = 0;

        // run for some time then show result
        #2000 $display ("Mem[200] = %2d, Mem[198] = %6d", 
                        mips.Mem[200], mips.Mem[198]);
    end

    // ---------------- WAVEFORM DUMP ----------------
    initial begin
        $dumpfile ("mips_pipeline.vcd");
        $dumpvars (0, test_processor);

        // dump pipeline registers for waveform
        $dumpvars (1, mips.IF_ID_IR, mips.IF_ID_NPC);
        $dumpvars (1, mips.ID_EX_IR, mips.ID_EX_NPC, mips.ID_EX_A, mips.ID_EX_B, mips.ID_EX_Imm);
        $dumpvars (1, mips.EX_MEM_IR, mips.EX_MEM_ALUOut, mips.EX_MEM_B);
        $dumpvars (1, mips.MEM_WB_IR, mips.MEM_WB_ALUOut, mips.MEM_WB_LMD);
    end
    
    initial begin
    $dumpfile("mips.vcd");
    $dumpvars(0, test_processor);   // sab signals dump

    // Specific pipeline signals dump
    $dumpvars(1, mips.IF_ID_IR, mips.ID_EX_IR, mips.EX_MEM_IR, mips.MEM_WB_IR);
    $dumpvars(1, mips.ID_EX_A, mips.ID_EX_B, mips.EX_MEM_ALUOut, mips.MEM_WB_ALUOut);
    $dumpvars(1, mips.Reg[2], mips.Reg[3], mips.Mem[200], mips.Mem[198]);
end


    // ---------------- MONITOR PIPELINE FLOW ----------------
    initial begin
        $monitor ($time,
                  " | PC=%d | IF/ID_IR=%h | ID/EX_IR=%h | EX/MEM_IR=%h | MEM/WB_IR=%h | R2=%d",
                  mips.PC,
                  mips.IF_ID_IR,
                  mips.ID_EX_IR,
                  mips.EX_MEM_IR,
                  mips.MEM_WB_IR,
                  mips.Reg[2]);
        #3000 $finish;
    end
endmodule

Processor_MIPS32-main/processor_pipeline/processor_pipeline.sim/sim_1/behav/xsim/mips_pipeline.vcd
$date
   Mon Aug 18 13:38:32 2025
$end

$version
  2024.1
  $dumpfile ("mips_pipeline.vcd") 
$end

$timescale
  1ps
$end

$scope module test_processor $end
$var reg 1 ! clk1 $end
$var reg 1 " clk2 $end
$var integer 32 # k [31:0] $end
$scope module mips $end
$var wire 1 $ clk1 $end
$var wire 1 % clk2 $end
$var reg 32 & PC [31:0] $end
$var reg 32 ' IF_ID_IR [31:0] $end
$var reg 32 ( IF_ID_NPC [31:0] $end
$var reg 32 ) ID_EX_IR [31:0] $end
$var reg 32 * ID_EX_NPC [31:0] $end
$var reg 32 + ID_EX_A [31:0] $end
$var reg 32 , ID_EX_B [31:0] $end
$var reg 32 - ID_EX_Imm [31:0] $end
$var reg 32 . EX_MEM_IR [31:0] $end
$var reg 32 / EX_MEM_ALUOut [31:0] $end
$var reg 32 0 EX_MEM_B [31:0] $end
$var reg 32 1 MEM_WB_IR [31:0] $end
$var reg 32 2 MEM_WB_ALUOut [31:0] $end
$var reg 32 3 MEM_WB_LMD [31:0] $end
$var reg 3 4 ID_EX_type [2:0] $end
$var reg 3 5 EX_MEM_type [2:0] $end
$var reg 3 6 MEM_WB_type [2:0] $end
$var reg 1 7 HALTED $end
$var reg 1 8 TAKEN_BRANCH $end
$upscope $end
$upscope $end
$enddefinitions $end

#0
$dumpvars
0!
0"
b11111 #
0$
0%
b0 &
bx '
bx (
bx )
bx *
bx +
bx ,
bx -
bx .
bx /
bx 0
b0 1
b0 2
b0 3
bx 4
bx 5
bx 6
07
08
$end

#5000
1!
1$

#7000
b1 &
b101000000010100000000011001000 '
b1 (

#10000
0!
0$

#15000
1"
1%
b0 +

#17000
b101000000010100000000011001000 )
b1 *
b1010 ,
b11001000 -
bx 1
b11 4

#20000
0"
0%

#25000
1!
1$
b101000000010100000000011001000 .
b11 5

#27000
b10 &
b101000000000100000000000000001 '
b10 (
b11001000 /
b1010 0

#30000
0!
0$

#35000
1"
1%
b11 6

#37000
b101000000000100000000000000001 )
b10 *
b10 ,
b1 -
b101000000010100000000011001000 1

#40000
0"
0%

#45000
1!
1$
b101000000000100000000000000001 .

#47000
b11 &
b1110100101001010000000000000 '
b11 (
b1 /
b10 0

#50000
0!
0$

#55000
1"
1%

#57000
b1110100101001010000000000000 )
b11 *
b10100 +
b10100 ,
b11111111111111111010000000000000 -
b101000000000100000000000000001 1
b0 4

#60000
0"
0%

#65000
1!
1$
b1110100101001010000000000000 .
b0 5

#67000
b100 &
b100001010000110000000000000000 '
b100 (
b10100 /

#70000
0!
0$

#75000
1"
1%
b0 6

#77000
b100001010000110000000000000000 )
b100 *
b1010 +
b11 ,
b0 -
b1110100101001010000000000000 1
b10100 2
b1 4

#80000
0"
0%

#85000
1!
1$
b100001010000110000000000000000 .
b1 5

#87000
b101 &
b1110100101001010000000000000 '
b101 (
b0 /

#90000
0!
0$

#95000
1"
1%
b1 6

#97000
b1110100101001010000000000000 )
b101 *
b10100 +
b10100 ,
b11111111111111111010000000000000 -
b100001010000110000000000000000 1
b0 2
b0 4

#100000
0"
0%

#105000
1!
1$
b1110100101001010000000000000 .
b0 5

#107000
b110 &
b10100010000110001000000000000 '
b110 (
b10100 /

#110000
0!
0$

#115000
1"
1%
b0 6

#117000
b10100010000110001000000000000 )
b110 *
b10 +
b0 ,
b1000000000000 -
b1110100101001010000000000000 1
b10100 2

#120000
0"
0%

#125000
1!
1$
b10100010000110001000000000000 .

#127000
b111 &
b101100011000110000000000000001 '
b111 (
b0 /

#130000
0!
0$

#135000
1"
1%

#137000
b101100011000110000000000000001 )
b111 *
b0 +
b1 -
b10100010000110001000000000000 1
b0 2
b100 4

#140000
0"
0%

#145000
1!
1$
b101100011000110000000000000001 .
b100 5

#147000
b1000 &
b1110100101001010000000000000 '
b1000 (

#150000
0!
0$

#155000
1"
1%
b100 6

#157000
b1110100101001010000000000000 )
b1000 *
b10100 +
b10100 ,
b11111111111111111010000000000000 -
b101100011000110000000000000001 1
b0 4

#160000
0"
0%

#165000
1!
1$
b1110100101001010000000000000 .
b0 5

#167000
b1001 &
b110100011000001111111111111100 '
b1001 (
b10100 /

#170000
0!
0$

#175000
1"
1%
b0 ,
b0 6

#177000
b110100011000001111111111111100 )
b1001 *
b0 +
b11111111111111111111111111111100 -
b1110100101001010000000000000 1
b10100 2
b101 4

#180000
0"
0%

#185000
1!
1$
b110100011000001111111111111100 .
b101 5

#187000
b1010 &
b100101010000101111111111111110 '
b1010 (

#190000
0!
0$

#195000
1"
1%
b101 6

#197000
b100101010000101111111111111110 )
b1010 *
b1010 +
b11111111111111111111111111111110 -
b110100011000001111111111111100 1
b10 4

#200000
0"
0%

#205000
1!
1$
b100101010000101111111111111110 .
b10 5

#207000
b1011 &
b11111100000000000000000000000000 '
b1011 (
b1000 /
b0 0
17

